slurmify/__init__.py
slurmify/cli.py
slurmify/job_submission.py
slurmify-0.1.4.dist-info/LICENSE
slurmify-0.1.4.dist-info/METADATA
slurmify-0.1.4.dist-info/WHEEL
slurmify-0.1.4.dist-info/entry_points.txt
slurmify-0.1.4.dist-info/top_level.txt
slurmify-0.1.4.dist-info/RECORD
