Metadata-Version: 2.1
Name: slurmify
Version: 0.1.4
Summary: A utility library for SLURM job management
Home-page: https://github.com/giannisdaras/slurmify
Author: Giannis Daras
Author-email: giannisdaras@utexas.edu
Classifier: Programming Language :: Python :: 3
Classifier: License :: OSI Approved :: MIT License
Classifier: Operating System :: OS Independent
Requires-Python: >=3.6
License-File: LICENSE
Requires-Dist: click
